colcon_clean/__init__.py
colcon_clean/base_handler/__init__.py
colcon_clean/base_handler/build.py
colcon_clean/base_handler/install.py
colcon_clean/base_handler/log.py
colcon_clean/base_handler/test_result.py
colcon_clean/clean/__init__.py
colcon_clean/clean/query.py
colcon_clean/subverb/__init__.py
colcon_clean/subverb/packages.py
colcon_clean/subverb/workspace.py
colcon_clean/verb/__init__.py
colcon_clean/verb/clean.py
colcon_clean-0.2.1.dist-info/LICENSE
colcon_clean-0.2.1.dist-info/METADATA
colcon_clean-0.2.1.dist-info/WHEEL
colcon_clean-0.2.1.dist-info/entry_points.txt
colcon_clean-0.2.1.dist-info/top_level.txt
colcon_clean-0.2.1.dist-info/zip-safe
colcon_clean-0.2.1.dist-info/RECORD
