Metadata-Version: 2.1
Name: colcon-clean
Version: 0.2.1
Summary: Extension for colcon to clean package workspaces.
Home-page: https://colcon.readthedocs.io
Author: Ruffin White
Author-email: roxfoxpox@gmail.com
Maintainer: Ruffin White
Maintainer-email: roxfoxpox@gmail.com
License: Apache License, Version 2.0
Project-URL: Changelog, https://github.com/colcon/colcon-clean/milestones?direction=desc&sort=due_date&state=closed
Project-URL: GitHub, https://github.com/colcon/colcon-clean/
Keywords: colcon
Platform: UNKNOWN
Classifier: Development Status :: 3 - Alpha
Classifier: Environment :: Plugins
Classifier: Intended Audience :: Developers
Classifier: License :: OSI Approved :: Apache Software License
Classifier: Operating System :: MacOS
Classifier: Operating System :: Microsoft :: Windows
Classifier: Operating System :: POSIX
Classifier: Programming Language :: Python
Classifier: Topic :: Software Development :: Build Tools
Requires-Python: >=3.6
License-File: LICENSE
Requires-Dist: colcon-core (>=0.5.2)
Requires-Dist: scantree (<0.0.2a0)
Requires-Dist: scandir ; platform_system == "Windows"
Provides-Extra: test
Requires-Dist: colcon-defaults ; extra == 'test'
Requires-Dist: colcon-package-information (>=0.3.3) ; extra == 'test'
Requires-Dist: colcon-package-selection (>=0.2.10) ; extra == 'test'
Requires-Dist: colcon-recursive-crawl ; extra == 'test'
Requires-Dist: colcon-test-result (>=0.3.8) ; extra == 'test'
Requires-Dist: flake8-blind-except ; extra == 'test'
Requires-Dist: flake8-builtins ; extra == 'test'
Requires-Dist: flake8-class-newline ; extra == 'test'
Requires-Dist: flake8-comprehensions ; extra == 'test'
Requires-Dist: flake8-deprecated ; extra == 'test'
Requires-Dist: flake8-docstrings ; extra == 'test'
Requires-Dist: flake8-import-order ; extra == 'test'
Requires-Dist: flake8-quotes ; extra == 'test'
Requires-Dist: flake8 (>=3.6.0) ; extra == 'test'
Requires-Dist: pep8-naming ; extra == 'test'
Requires-Dist: pylint ; extra == 'test'
Requires-Dist: pytest ; extra == 'test'
Requires-Dist: pytest-cov ; extra == 'test'
Requires-Dist: scspell3k (>=2.2) ; extra == 'test'
